rtl/full_adder.sv
module full_adder (
    input  logic A,
    input  logic B,
    input  logic Cin,

    output logic Sum,
    output logic Cout
);

    assign Sum  = A ^ B ^ Cin;

    assign Cout = (A & B) |
                  (A & Cin) |
                  (B & Cin);

endmodule

rtl/half_adder.sv
module half_adder (
    input  logic A,
    input  logic B,
    output logic Sum,
    output logic Cout
);

    assign Sum   = A ^ B;
    assign Cout = A & B;

endmodule

rtl/braun_multiplier_4x4.sv
module braun_multiplier_4x4 (
    input  logic [3:0] A,
    input  logic [3:0] B,
    output logic [7:0] Product
);

    // Partial Products
    logic pp00, pp01, pp02, pp03;
    logic pp10, pp11, pp12, pp13;
    logic pp20, pp21, pp22, pp23;
    logic pp30, pp31, pp32, pp33;

    // Intermediate Sums
    logic S1, S2, S3, S4;
    logic S5, S6;

    // Intermediate Carries
    logic C1, C2, C3, C4;
    logic C5, C6, C7, C8;
    logic C9, C10, C11;

    // Partial Product Generation
    assign pp00 = A[0] & B[0];
    assign pp01 = A[1] & B[0];
    assign pp02 = A[2] & B[0];
    assign pp03 = A[3] & B[0];

    assign pp10 = A[0] & B[1];
    assign pp11 = A[1] & B[1];
    assign pp12 = A[2] & B[1];
    assign pp13 = A[3] & B[1];

    assign pp20 = A[0] & B[2];
    assign pp21 = A[1] & B[2];
    assign pp22 = A[2] & B[2];
    assign pp23 = A[3] & B[2];

    assign pp30 = A[0] & B[3];
    assign pp31 = A[1] & B[3];
    assign pp32 = A[2] & B[3];
    assign pp33 = A[3] & B[3];

// Product Bit P0
assign Product[0] = pp00;

// HA1
half_adder HA1 (
    .A(pp01),
    .B(pp10),
    .Sum(Product[1]),
    .Cout(C1)
);


// FA1
full_adder FA1 (
    .A(pp11),
    .B(pp20),
    .Cin(C1),
    .Sum(S1),
    .Cout(C2)
);

// FA2
full_adder FA2 (
    .A(pp21),
    .B(pp30),
    .Cin(C2),
    .Sum(S2),
    .Cout(C3)
);

// HA2
half_adder HA2 (
    .A(pp31),
    .B(C3),
    .Sum(S3),
    .Cout(C4)
);

// HA3
half_adder HA3 (
    .A(pp02),
    .B(S1),
    .Sum(Product[2]),
    .Cout(C5)
);

// FA3
full_adder FA3 (
    .A(pp12),
    .B(S2),
    .Cin(C5),
    .Sum(S4),
    .Cout(C6)
);

// FA4
full_adder FA4 (
    .A(pp22),
    .B(S3),
    .Cin(C6),
    .Sum(S5),
    .Cout(C7)
);

// FA5
full_adder FA5 (
    .A(pp32),
    .B(C4),
    .Cin(C7),
    .Sum(S6),
    .Cout(C8)
);

// HA4
half_adder HA4 (
    .A(pp03),
    .B(S4),
    .Sum(Product[3]),
    .Cout(C9)
);

// FA6
full_adder FA6 (
    .A(pp13),
    .B(S5),
    .Cin(C9),
    .Sum(Product[4]),
    .Cout(C10)
);

// FA7
full_adder FA7 (
    .A(pp23),
    .B(S6),
    .Cin(C10),
    .Sum(Product[5]),
    .Cout(C11)
);

// FA8
full_adder FA8 (
    .A(pp33),
    .B(C8),
    .Cin(C11),
    .Sum(Product[6]),
    .Cout(Product[7])
);

endmodule

tb/tb_braun_multiplier_4x4.sv
`timescale 1ns/1ps

module tb_braun_multiplier_4x4;

    logic [3:0] A;
    logic [3:0] B;
    logic [7:0] Product;

    integer i, j;
    integer errors;

    // DUT
    braun_multiplier_4x4 uut (
        .A(A),
        .B(B),
        .Product(Product)
    );

    initial begin

        $dumpfile("waves/braun_multiplier_4x4.vcd");
        $dumpvars(0, tb_braun_multiplier_4x4);

        errors = 0;

        $display("--------------------------------------------");
        $display("Testing 4x4 Braun Multiplier");
        $display("--------------------------------------------");

        for (i = 0; i < 16; i = i + 1) begin
            for (j = 0; j < 16; j = j + 1) begin

                A = i;
                B = j;

                #10;

                if (Product !== (i * j)) begin
                    $display("ERROR : A=%0d B=%0d Expected=%0d Got=%0d",
                              i, j, (i*j), Product);
                    errors = errors + 1;
                end

            end
        end

        $display("--------------------------------------------");

        if (errors == 0)
            $display("All 256 test cases PASSED!");
        else
            $display("FAILED! Total Errors = %0d", errors);

        $display("--------------------------------------------");

        $finish;

    end

endmodule

waves/braun_multiplier_4x4.vcd
$date
	Mon Jul 27 02:46:19 2026
$end
$version
	Icarus Verilog
$end
$timescale
	1ps
$end
$scope module tb_braun_multiplier_4x4 $end
$var wire 8 ! Product [7:0] $end
$var reg 4 " A [3:0] $end
$var reg 4 # B [3:0] $end
$var integer 32 $ errors [31:0] $end
$var integer 32 % i [31:0] $end
$var integer 32 & j [31:0] $end
$scope module uut $end
$var wire 4 ' A [3:0] $end
$var wire 4 ( B [3:0] $end
$var wire 1 ) pp00 $end
$var wire 1 * pp01 $end
$var wire 1 + pp02 $end
$var wire 1 , pp03 $end
$var wire 1 - pp10 $end
$var wire 1 . pp11 $end
$var wire 1 / pp12 $end
$var wire 1 0 pp13 $end
$var wire 1 1 pp20 $end
$var wire 1 2 pp21 $end
$var wire 1 3 pp22 $end
$var wire 1 4 pp23 $end
$var wire 1 5 pp30 $end
$var wire 1 6 pp31 $end
$var wire 1 7 pp32 $end
$var wire 1 8 pp33 $end
$var wire 1 9 S6 $end
$var wire 1 : S5 $end
$var wire 1 ; S4 $end
$var wire 1 < S3 $end
$var wire 1 = S2 $end
$var wire 1 > S1 $end
$var wire 8 ? Product [7:0] $end
$var wire 1 @ C9 $end
$var wire 1 A C8 $end
$var wire 1 B C7 $end
$var wire 1 C C6 $end
$var wire 1 D C5 $end
$var wire 1 E C4 $end
$var wire 1 F C3 $end
$var wire 1 G C2 $end
$var wire 1 H C11 $end
$var wire 1 I C10 $end
$var wire 1 J C1 $end
$scope module FA1 $end
$var wire 1 . A $end
$var wire 1 1 B $end
$var wire 1 G Cout $end
$var wire 1 > Sum $end
$var wire 1 J Cin $end
$upscope $end
$scope module FA2 $end
$var wire 1 2 A $end
$var wire 1 5 B $end
$var wire 1 G Cin $end
$var wire 1 F Cout $end
$var wire 1 = Sum $end
$upscope $end
$scope module FA3 $end
$var wire 1 / A $end
$var wire 1 = B $end
$var wire 1 C Cout $end
$var wire 1 ; Sum $end
$var wire 1 D Cin $end
$upscope $end
$scope module FA4 $end
$var wire 1 3 A $end
$var wire 1 C Cin $end
$var wire 1 B Cout $end
$var wire 1 : Sum $end
$var wire 1 < B $end
$upscope $end
$scope module FA5 $end
$var wire 1 7 A $end
$var wire 1 B Cin $end
$var wire 1 A Cout $end
$var wire 1 9 Sum $end
$var wire 1 E B $end
$upscope $end
$scope module FA6 $end
$var wire 1 0 A $end
$var wire 1 : B $end
$var wire 1 I Cout $end
$var wire 1 K Sum $end
$var wire 1 @ Cin $end
$upscope $end
$scope module FA7 $end
$var wire 1 4 A $end
$var wire 1 9 B $end
$var wire 1 I Cin $end
$var wire 1 H Cout $end
$var wire 1 L Sum $end
$upscope $end
$scope module FA8 $end
$var wire 1 8 A $end
$var wire 1 A B $end
$var wire 1 H Cin $end
$var wire 1 M Cout $end
$var wire 1 N Sum $end
$upscope $end
$scope module HA1 $end
$var wire 1 * A $end
$var wire 1 - B $end
$var wire 1 J Cout $end
$var wire 1 O Sum $end
$upscope $end
$scope module HA2 $end
$var wire 1 6 A $end
$var wire 1 F B $end
$var wire 1 E Cout $end
$var wire 1 < Sum $end
$upscope $end
$scope module HA3 $end
$var wire 1 + A $end
$var wire 1 > B $end
$var wire 1 D Cout $end
$var wire 1 P Sum $end
$upscope $end
$scope module HA4 $end
$var wire 1 , A $end
$var wire 1 ; B $end
$var wire 1 @ Cout $end
$var wire 1 Q Sum $end
$upscope $end
$upscope $end
$upscope $end
$enddefinitions $end
$comment Show the parameter values. $end
$dumpall
$end
#0
$dumpvars
0Q
0P
0O
0N
0M
0L
0K
0J
0I
0H
0G
0F
0E
0D
0C
0B
0A
0@
b0 ?
0>
0=
0<
0;
0:
09
08
07
06
05
04
03
02
01
00
0/
0.
0-
0,
0+
0*
0)
b0 (
b0 '
b0 &
b0 %
b0 $
b0 #
b0 "
b0 !
$end
#10000
b1 #
b1 (
b1 &
#20000
b10 #
b10 (
b10 &
#30000
b11 #
b11 (
b11 &
#40000
b100 #
b100 (
b100 &
#50000
b101 #
b101 (
b101 &
#60000
b110 #
b110 (
b110 &
#70000
b111 #
b111 (
b111 &
#80000
b1000 #
b1000 (
b1000 &
#90000
b1001 #
b1001 (
b1001 &
#100000
b1010 #
b1010 (
b1010 &
#110000
b1011 #
b1011 (
b1011 &
#120000
b1100 #
b1100 (
b1100 &
#130000
b1101 #
b1101 (
b1101 &
#140000
b1110 #
b1110 (
b1110 &
#150000
b1111 #
b1111 (
b1111 &
#160000
b0 #
b0 (
b1 "
b1 '
b1 %
b0 &
#170000
b1 !
b1 ?
1)
b1 #
b1 (
b1 &
#180000
b10 !
b10 ?
1O
0)
1-
b10 #
b10 (
b10 &
#190000
b11 !
b11 ?
1)
b11 #
b11 (
b11 &
#200000
1P
b100 !
b100 ?
1>
0O
0)
0-
11
b100 #
b100 (
b100 &
#210000
b101 !
b101 ?
1)
b101 #
b101 (
b101 &
#220000
b110 !
b110 ?
1O
0)
1-
b110 #
b110 (
b110 &
#230000
b111 !
b111 ?
1)
b111 #
b111 (
b111 &
#240000
1Q
1;
0P
b1000 !
b1000 ?
0>
1=
0O
0)
0-
01
15
b1000 #
b1000 (
b1000 &
#250000
b1001 !
b1001 ?
1)
b1001 #
b1001 (
b1001 &
#260000
b1010 !
b1010 ?
1O
0)
1-
b1010 #
b1010 (
b1010 &
#270000
b1011 !
b1011 ?
1)
b1011 #
b1011 (
b1011 &
#280000
1P
b1100 !
b1100 ?
1>
0O
0)
0-
11
b1100 #
b1100 (
b1100 &
#290000
b1101 !
b1101 ?
1)
b1101 #
b1101 (
b1101 &
#300000
b1110 !
b1110 ?
1O
0)
1-
b1110 #
b1110 (
b1110 &
#310000
b1111 !
b1111 ?
1)
b1111 #
b1111 (
b1111 &
#320000
0Q
0;
0P
b0 !
b0 ?
0>
0=
0O
0)
0-
01
05
b0 #
b0 (
b10 "
b10 '
b10 %
b0 &
#330000
b10 !
b10 ?
1O
1*
b1 #
b1 (
b1 &
#340000
b100 !
b100 ?
1P
1>
0O
0*
1.
b10 #
b10 (
b10 &
#350000
b110 !
b110 ?
1O
1*
b11 #
b11 (
b11 &
#360000
1Q
1;
b1000 !
b1000 ?
0P
0>
1=
0O
0*
0.
12
b100 #
b100 (
b100 &
#370000
b1010 !
b1010 ?
1O
1*
b101 #
b101 (
b101 &
#380000
b1100 !
b1100 ?
1P
1>
0O
0*
1.
b110 #
b110 (
b110 &
#390000
b1110 !
b1110 ?
1O
1*
b111 #
b111 (
b111 &
#400000
0Q
1K
0;
b10000 !
b10000 ?
0P
1:
0>
0=
0O
1<
0*
0.
02
16
b1000 #
b1000 (
b1000 &
#410000
b10010 !
b10010 ?
1O
1*
b1001 #
b1001 (
b1001 &
#420000
b10100 !
b10100 ?
1P
1>
0O
0*
1.
b1010 #
b1010 (
b1010 &
#430000
b10110 !
b10110 ?
1O
1*
b1011 #
b1011 (
b1011 &
#440000
1Q
1;
b11000 !
b11000 ?
0P
0>
1=
0O
0*
0.
12
b1100 #
b1100 (
b1100 &
#450000
b11010 !
b11010 ?
1O
1*
b1101 #
b1101 (
b1101 &
#460000
b11100 !
b11100 ?
1P
1>
0O
0*
1.
b1110 #
b1110 (
b1110 &
#470000
b11110 !
b11110 ?
1O
1*
b1111 #
b1111 (
b1111 &
#480000
0Q
0K
0;
b0 !
b0 ?
0P
0:
0>
0=
0O
0<
0*
0.
02
06
b0 #
b0 (
b11 "
b11 '
b11 %
b0 &
#490000
b11 !
b11 ?
1O
1)
1*
b1 #
b1 (
b1 &
#500000
1P
b110 !
b110 ?
1>
0)
0*
1-
1.
b10 #
b10 (
b10 &
#510000
1Q
1;
1=
1G
0P
b1001 !
b1001 ?
0>
0O
1J
1)
1*
b11 #
b11 (
b11 &
#520000
0K
0:
1Q
1;
0<
1P
0G
0F
b1100 !
b1100 ?
1>
1=
0J
0)
0*
0-
0.
11
12
b100 #
b100 (
b100 &
#530000
b1111 !
b1111 ?
1O
1)
1*
b101 #
b101 (
b101 &
#540000
1K
1:
0Q
1<
0;
1F
0=
0P
1G
b10010 !
b10010 ?
0>
0)
0*
1-
1.
b110 #
b110 (
b110 &
#550000
1P
b10101 !
b10101 ?
1>
0O
1J
1)
1*
b111 #
b111 (
b111 &
#560000
1Q
1;
0F
1K
0L
1=
0P
0G
1:
09
b11000 !
b11000 ?
0>
0J
1<
0E
0)
0*
0-
0.
01
02
15
16
b1000 #
b1000 (
b1000 &
#570000
b11011 !
b11011 ?
1O
1)
1*
b1001 #
b1001 (
b1001 &
#580000
1P
b11110 !
b11110 ?
1>
0)
0*
1-
1.
b1010 #
b1010 (
b1010 &
#590000
0K
1L
0:
19
0Q
0;
0<
1E
1F
0=
1G
0P
b100001 !
b100001 ?
0>
0O
1J
1)
1*
b1011 #
b1011 (
b1011 &
#600000
0Q
0;
1P
0G
b100100 !
b100100 ?
1>
0=
0J
0)
0*
0-
0.
11
12
b1100 #
b1100 (
b1100 &
#610000
b100111 !
b100111 ?
1O
1)
1*
b1101 #
b1101 (
b1101 &
#620000
1Q
1;
1=
0P
1G
b101010 !
b101010 ?
0>
0)
0*
1-
1.
b1110 #
b1110 (
b1110 &
#630000
1P
b101101 !
b101101 ?
1>
0O
1J
1)
1*
b1111 #
b1111 (
b1111 &
#640000
0Q
0;
0K
0L
0=
0P
0G
0F
0:
09
b0 !
b0 ?
0>
0J
0<
0E
0)
0*
0-
0.
01
02
05
06
b0 #
b0 (
b100 "
b100 '
b100 %
b0 &
#650000
b100 !
b100 ?
1P
1+
b1 #
b1 (
b1 &
#660000
b1000 !
b1000 ?
1Q
1;
0P
0+
1/
b10 #
b10 (
b10 &
#670000
b1100 !
b1100 ?
1P
1+
b11 #
b11 (
b11 &
#680000
1K
b10000 !
b10000 ?
0Q
0;
1:
0P
0+
0/
13
b100 #
b100 (
b100 &
#690000
b10100 !
b10100 ?
1P
1+
b101 #
b101 (
b101 &
#700000
b11000 !
b11000 ?
1Q
1;
0P
0+
1/
b110 #
b110 (
b110 &
#710000
b11100 !
b11100 ?
1P
1+
b111 #
b111 (
b111 &
#720000
0K
1L
b100000 !
b100000 ?
0Q
0;
0:
19
0P
0+
0/
03
17
b1000 #
b1000 (
b1000 &
#730000
b100100 !
b100100 ?
1P
1+
b1001 #
b1001 (
b1001 &
#740000
b101000 !
b101000 ?
1Q
1;
0P
0+
1/
b1010 #
b1010 (
b1010 &
#750000
b101100 !
b101100 ?
1P
1+
b1011 #
b1011 (
b1011 &
#760000
1K
b110000 !
b110000 ?
0Q
0;
1:
0P
0+
0/
13
b1100 #
b1100 (
b1100 &
#770000
b110100 !
b110100 ?
1P
1+
b1101 #
b1101 (
b1101 &
#780000
b111000 !
b111000 ?
1Q
1;
0P
0+
1/
b1110 #
b1110 (
b1110 &
#790000
b111100 !
b111100 ?
1P
1+
b1111 #
b1111 (
b1111 &
#800000
0K
0L
b0 !
b0 ?
0Q
0;
0:
09
0P
0+
0/
03
07
b0 #
b0 (
b101 "
b101 '
b101 %
b0 &
#810000
b101 !
b101 ?
1P
1)
1+
b1 #
b1 (
b1 &
#820000
1Q
b1010 !
b1010 ?
1;
0P
1O
0)
0+
1-
1/
b10 #
b10 (
b10 &
#830000
b1111 !
b1111 ?
1P
1)
1+
b11 #
b11 (
b11 &
#840000
1K
0Q
b10100 !
b10100 ?
0;
1>
1:
1P
0O
0)
0+
0-
0/
11
13
b100 #
b100 (
b100 &
#850000
1Q
b11001 !
b11001 ?
1;
0P
1D
1)
1+
b101 #
b101 (
b101 &
#860000
0L
09
1K
0B
1:
0C
b11110 !
b11110 ?
1P
0D
1O
0)
0+
1-
1/
b110 #
b110 (
b110 &
#870000
1L
19
0K
1B
0:
1C
0Q
b100011 !
b100011 ?
0;
0P
1D
1)
1+
b111 #
b111 (
b111 &
#880000
1Q
0N
0K
1;
1L
0C
0B
0A
b101000 !
b101000 ?
0>
0:
1=
19
0P
0D
0O
0)
0+
0-
0/
01
03
15
17
b1000 #
b1000 (
b1000 &
#890000
b101101 !
b101101 ?
1P
1)
1+
b1001 #
b1001 (
b1001 &
#900000
1K
1:
0Q
1C
b110010 !
b110010 ?
0;
0P
1O
0)
0+
1-
1/
b1010 #
b1010 (
b1010 &
#910000
b110111 !
b110111 ?
1P
1)
1+
b1011 #
b1011 (
b1011 &
#920000
0N
1L
0A
1K
19
1Q
0C
0B
b111100 !
b111100 ?
1;
1>
1:
1P
0O
0)
0+
0-
0/
11
13
b1100 #
b1100 (
b1100 &
#930000
1N
0L
1A
09
0K
1B
0:
1C
0Q
b1000001 !
b1000001 ?
0;
0P
1D
1)
1+
b1101 #
b1101 (
b1101 &
#940000
b1000110 !
b1000110 ?
1P
0D
1O
0)
0+
1-
1/
b1110 #
b1110 (
b1110 &
#950000
1Q
b1001011 !
b1001011 ?
1;
0P
1D
1)
1+
b1111 #
b1111 (
b1111 &
#960000
0N
0Q
0K
0L
0;
0C
0B
0A
0:
09
b0 !
b0 ?
0>
0=
0P
0D
0O
0+
0/
03
07
0)
0-
01
05
b0 #
b0 (
b110 "
b110 '
b110 %
b0 &
#970000
b110 !
b110 ?
1O
1P
1*
1+
b1 #
b1 (
b1 &
#980000
b1100 !
b1100 ?
1Q
1>
1;
0O
1P
0*
0+
1.
1/
b10 #
b10 (
b10 &
#990000
1K
1:
1C
b10010 !
b10010 ?
0Q
0;
1O
0P
1D
1*
1+
b11 #
b11 (
b11 &
#1000000
0L
1Q
1;
1K
09
b11000 !
b11000 ?
0C
0B
0>
1=
1:
0O
0P
0D
0*
0+
0.
0/
12
13
b100 #
b100 (
b100 &
#1010000
b11110 !
b11110 ?
1O
1P
1*
1+
b101 #
b101 (
b101 &
#1020000
1L
19
0K
1B
0:
b100100 !
b100100 ?
0Q
1C
1>
0;
0O
1P
0*
0+
1.
1/
b110 #
b110 (
b110 &
#1030000
b101010 !
b101010 ?
1Q
1;
1O
0P
1D
1*
1+
b111 #
b111 (
b111 &
#1040000
1K
0B
0Q
0N
1:
0;
1L
b110000 !
b110000 ?
0C
0A
0>
0=
19
0O
0P
0D
1<
0*
0+
0.
0/
02
03
16
17
b1000 #
b1000 (
b1000 &
#1050000
b110110 !
b110110 ?
1O
1P
1*
1+
b1001 #
b1001 (
b1001 &
#1060000
b111100 !
b111100 ?
1Q
1>
1;
0O
1P
0*
0+
1.
1/
b1010 #
b1010 (
b1010 &
#1070000
1N
0L
1A
0K
09
1B
0:
1C
b1000010 !
b1000010 ?
0Q
0;
1O
0P
1D
1*
1+
b1011 #
b1011 (
b1011 &
#1080000
1Q
1;
0K
b1001000 !
b1001000 ?
0C
0>
1=
0:
0O
0P
0D
0*
0+
0.
0/
12
13
b1100 #
b1100 (
b1100 &
#1090000
b1001110 !
b1001110 ?
1O
1P
1*
1+
b1101 #
b1101 (
b1101 &
#1100000
1K
1:
b1010100 !
b1010100 ?
0Q
1C
1>
0;
0O
1P
0*
0+
1.
1/
b1110 #
b1110 (
b1110 &
#1110000
b1011010 !
b1011010 ?
1Q
1;
1O
0P
1D
1*
1+
b1111 #
b1111 (
b1111 &
#1120000
0K
0Q
0N
0:
0;
0L
b0 !
b0 ?
0C
0B
0A
0>
0=
09
0O
0P
0D
0<
0*
0+
0.
0/
02
03
06
07
b0 #
b0 (
b111 "
b111 '
b111 %
b0 &
#1130000
b111 !
b111 ?
1O
1P
1)
1*
1+
b1 #
b1 (
b1 &
#1140000
1Q
b1110 !
b1110 ?
1>
1;
1P
0)
0*
0+
1-
1.
1/
b10 #
b10 (
b10 &
#1150000
1K
1=
1:
1G
1C
0Q
b10101 !
b10101 ?
0>
0;
0O
1J
1P
0D
1)
1*
1+
b11 #
b11 (
b11 &
#1160000
0L
0<
1K
09
0G
1Q
0C
0F
0B
b11100 !
b11100 ?
1>
1;
1=
1:
1P
0J
0)
0*
0+
0-
0.
0/
11
12
13
b100 #
b100 (
b100 &
#1170000
1L
19
0K
1B
0:
1C
0Q
b100011 !
b100011 ?
0;
1O
0P
1D
1)
1*
1+
b101 #
b101 (
b101 &
#1180000
1Q
0C
1<
1;
1F
0=
1G
b101010 !
b101010 ?
0>
0P
0D
0)
0*
0+
1-
1.
1/
b110 #
b110 (
b110 &
#1190000
1K
1:
1C
0Q
0;
1D
b110001 !
b110001 ?
1>
0O
1J
0P
1)
1*
1+
b111 #
b111 (
b111 &
#1200000
1Q
1K
1;
0F
0N
1:
1=
1L
0C
0G
0B
0A
b111000 !
b111000 ?
0>
19
0P
0D
0J
1<
0E
0)
0*
0+
0-
0.
0/
01
02
03
15
16
17
b1000 #
b1000 (
b1000 &
#1210000
b111111 !
b111111 ?
1O
1P
1)
1*
1+
b1001 #
b1001 (
b1001 &
#1220000
1N
0L
1A
0K
09
1B
0:
0Q
1C
b1000110 !
b1000110 ?
1>
0;
1P
0)
0*
0+
1-
1.
1/
b1010 #
b1010 (
b1010 &
#1230000
0L
0B
09
0C
0<
1E
1F
0=
1G
1Q
b1001101 !
b1001101 ?
0>
1;
0O
1J
1P
0D
1)
1*
1+
b1011 #
b1011 (
b1011 &
#1240000
1K
0G
0Q
b1010100 !
b1010100 ?
1>
0;
0=
1:
1P
0J
0)
0*
0+
0-
0.
0/
11
12
13
b1100 #
b1100 (
b1100 &
#1250000
1Q
b1011011 !
b1011011 ?
1;
1O
0P
1D
1)
1*
1+
b1101 #
b1101 (
b1101 &
#1260000
1L
0Q
19
0;
0K
1B
1=
0:
1G
1C
b1100010 !
b1100010 ?
0>
0P
0D
0)
0*
0+
1-
1.
1/
b1110 #
b1110 (
b1110 &
#1270000
1Q
1;
1D
b1101001 !
b1101001 ?
1>
0O
1J
0P
1)
1*
1+
b1111 #
b1111 (
b1111 &
#1280000
0Q
0K
0;
0B
0N
0:
0=
0L
0C
0G
0F
0A
b0 !
b0 ?
0>
09
0P
0D
0J
0<
0E
0)
0*
0+
0-
0.
0/
01
02
03
05
06
07
b0 #
b0 (
b1000 "
b1000 '
b1000 %
b0 &
#1290000
b1000 !
b1000 ?
1Q
1,
b1 #
b1 (
b1 &
#1300000
b10000 !
b10000 ?
1K
0Q
0,
10
b10 #
b10 (
b10 &
#1310000
b11000 !
b11000 ?
1Q
1,
b11 #
b11 (
b11 &
#1320000
b100000 !
b100000 ?
0K
1L
0Q
0,
00
14
b100 #
b100 (
b100 &
#1330000
b101000 !
b101000 ?
1Q
1,
b101 #
b101 (
b101 &
#1340000
b110000 !
b110000 ?
1K
0Q
0,
10
b110 #
b110 (
b110 &
#1350000
b111000 !
b111000 ?
1Q
1,
b111 #
b111 (
b111 &
#1360000
b1000000 !
b1000000 ?
0K
0L
1N
0Q
0,
00
04
18
b1000 #
b1000 (
b1000 &
#1370000
b1001000 !
b1001000 ?
1Q
1,
b1001 #
b1001 (
b1001 &
#1380000
b1010000 !
b1010000 ?
1K
0Q
0,
10
b1010 #
b1010 (
b1010 &
#1390000
b1011000 !
b1011000 ?
1Q
1,
b1011 #
b1011 (
b1011 &
#1400000
b1100000 !
b1100000 ?
0K
1L
0Q
0,
00
14
b1100 #
b1100 (
b1100 &
#1410000
b1101000 !
b1101000 ?
1Q
1,
b1101 #
b1101 (
b1101 &
#1420000
b1110000 !
b1110000 ?
1K
0Q
0,
10
b1110 #
b1110 (
b1110 &
#1430000
b1111000 !
b1111000 ?
1Q
1,
b1111 #
b1111 (
b1111 &
#1440000
b0 !
b0 ?
0K
0L
0N
0Q
0,
00
04
08
b0 #
b0 (
b1001 "
b1001 '
b1001 %
b0 &
#1450000
b1001 !
b1001 ?
1Q
1)
1,
b1 #
b1 (
b1 &
#1460000
b10010 !
b10010 ?
1K
0Q
1O
0)
0,
1-
10
b10 #
b10 (
b10 &
#1470000
b11011 !
b11011 ?
1Q
1)
1,
b11 #
b11 (
b11 &
#1480000
1P
b100100 !
b100100 ?
0K
1>
1L
0Q
0O
0)
0,
0-
00
11
14
b100 #
b100 (
b100 &
#1490000
b101101 !
b101101 ?
1Q
1)
1,
b101 #
b101 (
b101 &
#1500000
b110110 !
b110110 ?
1K
0Q
1O
0)
0,
1-
10
b110 #
b110 (
b110 &
#1510000
b111111 !
b111111 ?
1Q
1)
1,
b111 #
b111 (
b111 &
#1520000
1;
0P
b1001000 !
b1001000 ?
0K
0>
0L
1=
1N
1Q
0O
0)
0,
0-
00
01
04
15
18
b1000 #
b1000 (
b1000 &
#1530000
b1010001 !
b1010001 ?
1K
0Q
1@
1)
1,
b1001 #
b1001 (
b1001 &
#1540000
0L
0I
b1011010 !
b1011010 ?
1Q
0@
1O
0)
0,
1-
10
b1010 #
b1010 (
b1010 &
#1550000
1L
1I
b1100011 !
b1100011 ?
0K
0Q
1@
1)
1,
b1011 #
b1011 (
b1011 &
#1560000
0M
1N
0I
1P
0H
b1101100 !
b1101100 ?
1>
1L
1Q
0@
0O
0)
0,
0-
00
11
14
b1100 #
b1100 (
b1100 &
#1570000
b1110101 !
b1110101 ?
1K
0Q
1@
1)
1,
b1101 #
b1101 (
b1101 &
#1580000
0M
1N
0H
1L
0I
b1111110 !
b1111110 ?
1Q
0@
1O
0)
0,
1-
10
b1110 #
b1110 (
b1110 &
#1590000
1M
0N
1H
0L
1I
b10000111 !
b10000111 ?
0K
0Q
1@
1)
1,
b1111 #
b1111 (
b1111 &
#1600000
0;
0I
0H
0M
0P
0L
0N
b0 !
b0 ?
0>
0=
0Q
0@
0O
0,
00
04
08
0)
0-
01
05
b0 #
b0 (
b1010 "
b1010 '
b1010 %
b0 &
#1610000
b1010 !
b1010 ?
1O
1Q
1*
1,
b1 #
b1 (
b1 &
#1620000
b10100 !
b10100 ?
1P
1>
1K
0O
0Q
0*
0,
1.
10
b10 #
b10 (
b10 &
#1630000
b11110 !
b11110 ?
1O
1Q
1*
1,
b11 #
b11 (
b11 &
#1640000
1;
b101000 !
b101000 ?
0P
0>
0K
1=
1L
0O
1Q
0*
0,
0.
00
12
14
b100 #
b100 (
b100 &
#1650000
b110010 !
b110010 ?
1K
1O
0Q
1@
1*
1,
b101 #
b101 (
b101 &
#1660000
0N
0H
1L
b111100 !
b111100 ?
1P
0I
1>
0O
1Q
0@
0*
0,
1.
10
b110 #
b110 (
b110 &
#1670000
1N
1H
0L
1I
b1000110 !
b1000110 ?
0K
1O
0Q
1@
1*
1,
b111 #
b111 (
b111 &
#1680000
1K
0;
b1010000 !
b1010000 ?
0P
0I
0H
1:
0M
0>
0=
0L
1N
0O
0Q
0@
1<
0*
0,
0.
00
02
04
16
18
b1000 #
b1000 (
b1000 &
#1690000
b1011010 !
b1011010 ?
1O
1Q
1*
1,
b1001 #
b1001 (
b1001 &
#1700000
1L
b1100100 !
b1100100 ?
1P
1I
1>
0K
0O
0Q
0*
0,
1.
10
b1010 #
b1010 (
b1010 &
#1710000
b1101110 !
b1101110 ?
1O
1Q
1*
1,
b1011 #
b1011 (
b1011 &
#1720000
0M
1;
1N
b1111000 !
b1111000 ?
0P
0I
0H
0>
1K
1=
1L
0O
1Q
0*
0,
0.
00
12
14
b1100 #
b1100 (
b1100 &
#1730000
1M
0N
1H
0L
b10000010 !
b10000010 ?
1I
0K
1O
0Q
1@
1*
1,
b1101 #
b1101 (
b1101 &
#1740000
b10001100 !
b10001100 ?
1P
1>
0O
1Q
0@
0*
0,
1.
10
b1110 #
b1110 (
b1110 &
#1750000
b10010110 !
b10010110 ?
1K
1O
0Q
1@
1*
1,
b1111 #
b1111 (
b1111 &
#1760000
0K
0;
b0 !
b0 ?
0P
0I
0H
0:
0M
0>
0=
0L
0N
0O
0Q
0@
0<
0*
0,
0.
00
02
04
06
08
b0 #
b0 (
b1011 "
b1011 '
b1011 %
b0 &
#1770000
b1011 !
b1011 ?
1O
1Q
1)
1*
1,
b1 #
b1 (
b1 &
#1780000
1P
b10110 !
b10110 ?
1>
1K
0Q
0)
0*
0,
1-
1.
10
b10 #
b10 (
b10 &
#1790000
1L
1I
0K
1@
1;
1=
1G
0P
b100001 !
b100001 ?
0>
0O
1J
0Q
1)
1*
1,
b11 #
b11 (
b11 &
#1800000
0K
0:
1;
0<
0N
1P
0G
0I
0F
0H
b101100 !
b101100 ?
1>
1=
1L
1Q
0@
0J
0)
0*
0,
0-
0.
00
11
12
14
b100 #
b100 (
b100 &
#1810000
b110111 !
b110111 ?
1K
1O
0Q
1@
1)
1*
1,
b101 #
b101 (
b101 &
#1820000
0K
1:
1<
1N
0;
1F
1H
0=
0L
0P
1G
1I
b1000010 !
b1000010 ?
0>
0Q
0@
0)
0*
0,
1-
1.
10
b110 #
b110 (
b110 &
#1830000
1P
b1001101 !
b1001101 ?
1>
0O
1J
1Q
1)
1*
1,
b111 #
b111 (
b111 &
#1840000
1;
0F
1=
0P
0I
0G
0H
1:
09
0M
b1011000 !
b1011000 ?
0>
1K
0L
1N
1Q
0J
1<
0E
0)
0*
0,
0-
0.
00
01
02
04
15
16
18
b1000 #
b1000 (
b1000 &
#1850000
1L
1I
b1100011 !
b1100011 ?
0K
1O
0Q
1@
1)
1*
1,
b1001 #
b1001 (
b1001 &
#1860000
1P
b1101110 !
b1101110 ?
1>
1Q
0@
0)
0*
0,
1-
1.
10
b1010 #
b1010 (
b1010 &
#1870000
0M
1N
0H
0I
0:
19
0;
0<
1E
1F
0=
1G
0P
b1111001 !
b1111001 ?
0>
1K
0O
1J
1Q
0@
1)
1*
1,
b1011 #
b1011 (
b1011 &
#1880000
1M
0;
0N
1P
0G
1H
b10000100 !
b10000100 ?
1>
0K
0=
0L
0Q
0J
0)
0*
0,
0-
0.
00
11
12
14
b1100 #
b1100 (
b1100 &
#1890000
b10001111 !
b10001111 ?
1O
1Q
1)
1*
1,
b1101 #
b1101 (
b1101 &
