rtl/d_flip_flop.sv
module d_flip_flop (

    input  logic clk,
    input  logic rst,
    input  logic D,

    output logic Q

);

    always_ff @(posedge clk or posedge rst)
    begin
        if (rst)
            Q <= 1'b0;
        else
            Q <= D;
    end

endmodule

tb/tb_d_flip_flop.sv
`timescale 1ns/1ps

module tb_d_flip_flop;

    logic clk;
    logic rst;
    logic D;
    logic Q;

    //-------------------------------------------------
    // Instantiate DUT
    //-------------------------------------------------

    d_flip_flop DUT (
        .clk(clk),
        .rst(rst),
        .D(D),
        .Q(Q)
    );

    //-------------------------------------------------
    // Clock Generation (10 ns period)
    //-------------------------------------------------

    initial begin
        clk = 0;
        forever #5 clk = ~clk;
    end

    //-------------------------------------------------
    // Stimulus
    //-------------------------------------------------

    initial begin

        $dumpfile("waves/d_flip_flop.vcd");
        $dumpvars(0, tb_d_flip_flop);

        // Apply Reset
        rst = 1;
        D   = 0;
        #10;

        // Release Reset
        rst = 0;

        D = 1;
        #10;

        D = 0;
        #10;

        D = 1;
        #10;

        D = 1;
        #10;

        D = 0;
        #10;

        $finish;

    end

    //-------------------------------------------------
    // Monitor
    //-------------------------------------------------

    initial begin
        $monitor(
            "Time=%0t clk=%b rst=%b D=%b Q=%b",
            $time, clk, rst, D, Q
        );
    end

endmodule

waves/d_flip_flop.vcd
$date
	Wed Jul 29 18:44:06 2026
$end
$version
	Icarus Verilog
$end
$timescale
	1ps
$end
$scope module tb_d_flip_flop $end
$var wire 1 ! Q $end
$var reg 1 " D $end
$var reg 1 # clk $end
$var reg 1 $ rst $end
$scope module DUT $end
$var wire 1 " D $end
$var wire 1 # clk $end
$var wire 1 $ rst $end
$var reg 1 ! Q $end
$upscope $end
$upscope $end
$enddefinitions $end
$comment Show the parameter values. $end
$dumpall
$end
#0
$dumpvars
1$
0#
0"
0!
$end
#5000
1#
#10000
0#
1"
0$
#15000
1!
1#
#20000
0#
0"
#25000
0!
1#
#30000
0#
1"
#35000
1!
1#
#40000
0#
#45000
1#
#50000
0#
0"
#55000
0!
1#
