rtl/full_adder.sv
module full_adder (
    input  logic A,
    input  logic B,
    input  logic Cin,

    output logic Sum,
    output logic Cout
);

    assign Sum  = A ^ B ^ Cin;

    assign Cout = (A & B) |
                  (A & Cin) |
                  (B & Cin);

endmodule

tb/tb_full_adder.sv
`timescale 1ns/1ps

module tb_full_adder;

    logic A;
    logic B;
    logic Cin;

    logic Sum;
    logic Cout;

    full_adder uut (
        .A(A),
        .B(B),
        .Cin(Cin),
        .Sum(Sum),
        .Cout(Cout)
    );

    
    initial begin

        $dumpfile("waves/full_adder.vcd");
        $dumpvars(0, tb_full_adder);

        $display("A B Cin | Sum Cout");
        $display("-------------------");

        for (int i = 0; i < 8; i++) begin
            {A, B, Cin} = i;
            #10;
            $display("%b %b %b |  %b    %b",
                     A, B, Cin, Sum, Cout);
        end

        $finish;
    end

endmodule

waves/full_adder.vcd
$date
	Fri Jul 24 19:21:07 2026
$end
$version
	Icarus Verilog
$end
$timescale
	1ps
$end
$scope module tb_full_adder $end
$var wire 1 ! Sum $end
$var wire 1 " Cout $end
$var reg 1 # A $end
$var reg 1 $ B $end
$var reg 1 % Cin $end
$scope module uut $end
$var wire 1 # A $end
$var wire 1 $ B $end
$var wire 1 % Cin $end
$var wire 1 " Cout $end
$var wire 1 ! Sum $end
$upscope $end
$scope begin $ivl_for_loop0 $end
$var integer 32 & i [31:0] $end
$upscope $end
$upscope $end
$enddefinitions $end
$comment Show the parameter values. $end
$dumpall
$end
#0
$dumpvars
b0 &
0%
0$
0#
0"
0!
$end
#10000
1!
1%
b1 &
#20000
1!
1$
0%
b10 &
#30000
1"
0!
1%
b11 &
#40000
0"
1!
1#
0$
0%
b100 &
#50000
1"
0!
1%
b101 &
#60000
0!
1$
0%
b110 &
#70000
1!
1%
b111 &
#80000
b1000 &
